setup.py
dlds_eval.egg-info/PKG-INFO
dlds_eval.egg-info/SOURCES.txt
dlds_eval.egg-info/dependency_links.txt
dlds_eval.egg-info/requires.txt
dlds_eval.egg-info/top_level.txt
dldseval/__init__.py
dldseval/utils.py
dldseval/classification/__init__.py
dldseval/classification/metrics.py
dldseval/detection/__init__.py
dldseval/detection/metrics.py